libversion/VersionUtil.py
libversion/__init__.py
libversion/version.py
team_14_lib_version-5.0.1.dist-info/METADATA
team_14_lib_version-5.0.1.dist-info/WHEEL
team_14_lib_version-5.0.1.dist-info/top_level.txt
team_14_lib_version-5.0.1.dist-info/RECORD
