Metadata-Version: 2.1
Name: team-14-lib-version
Version: 5.0.1
Summary: version aware library
Home-page: https://github.com/remla2024-team14/lib-version
Author: Team 14
Author-email: justinluu2000@gmail.com
Classifier: Programming Language :: Python :: 3
Classifier: License :: OSI Approved :: MIT License
Classifier: Operating System :: OS Independent
Requires-Python: >=3.8
Provides-Extra: dev
Requires-Dist: twine >=4.0.2 ; extra == 'dev'
